public_transit_client/__init__.py
public_transit_client/client.py
public_transit_client/model.py
public_transit_client/py.typed
public_transit_client-1.0.1.dist-info/LICENSE
public_transit_client-1.0.1.dist-info/METADATA
public_transit_client-1.0.1.dist-info/WHEEL
public_transit_client-1.0.1.dist-info/RECORD
