Metadata-Version: 2.1
Name: public-transit-client
Version: 1.0.1
Summary: Client to access the public transit service API endpoints.
Home-page: https://pypi.org/project/public-transit-client/
License: MIT
Author: Lukas Connolly
Author-email: lukas@connolly.ch
Requires-Python: >=3.12,<4.0
Classifier: License :: OSI Approved :: MIT License
Classifier: Programming Language :: Python :: 3
Classifier: Programming Language :: Python :: 3.12
Requires-Dist: geopy (>=2.4.1,<3.0.0)
Requires-Dist: pydantic (>=2.8.2,<3.0.0)
Requires-Dist: requests (>=2.32.3,<3.0.0)
Project-URL: Documentation, https://naviqore.github.io/documentation/introduction.html
Project-URL: Repository, https://github.com/naviqore/public-transit-client
